botometer/__init__.py
botometer-2.0.1.dist-info/LICENSE.txt
botometer-2.0.1.dist-info/METADATA
botometer-2.0.1.dist-info/WHEEL
botometer-2.0.1.dist-info/top_level.txt
botometer-2.0.1.dist-info/RECORD
